guniflask/.DS_Store
guniflask/__init__.py
guniflask/annotation/__init__.py
guniflask/annotation/core.py
guniflask/app/__init__.py
guniflask/app/factory.py
guniflask/app/initializer.py
guniflask/beans/__init__.py
guniflask/beans/annotation.py
guniflask/beans/autowired_post_processor.py
guniflask/beans/constructor_resolver.py
guniflask/beans/default_factory.py
guniflask/beans/definition.py
guniflask/beans/definition_registry.py
guniflask/beans/errors.py
guniflask/beans/factory.py
guniflask/beans/factory_hook.py
guniflask/beans/factory_post_processor.py
guniflask/beans/name_generator.py
guniflask/beans/post_processor.py
guniflask/beans/singleton_registry.py
guniflask/config/__init__.py
guniflask/config/app_config.py
guniflask/consul/__init__.py
guniflask/consul/client.py
guniflask/consul/errors.py
guniflask/context/__init__.py
guniflask/context/annotation.py
guniflask/context/annotation_config_registry.py
guniflask/context/annotation_config_utils.py
guniflask/context/bean_context.py
guniflask/context/bean_name_generator.py
guniflask/context/condition.py
guniflask/context/condition_evaluator.py
guniflask/context/config_constants.py
guniflask/context/config_post_processor.py
guniflask/context/context_aware_processor.py
guniflask/context/default_bean_context.py
guniflask/context/event.py
guniflask/context/event_listener.py
guniflask/context/event_publisher.py
guniflask/oauth2/__init__.py
guniflask/oauth2/abstract_endpoint.py
guniflask/oauth2/authentication.py
guniflask/oauth2/authentication_details.py
guniflask/oauth2/authentication_filter.py
guniflask/oauth2/authentication_manager.py
guniflask/oauth2/client_details.py
guniflask/oauth2/client_details_service.py
guniflask/oauth2/client_details_user_details_service.py
guniflask/oauth2/client_grant.py
guniflask/oauth2/errors.py
guniflask/oauth2/oauth2_utils.py
guniflask/oauth2/password_grant.py
guniflask/oauth2/refresh_grant.py
guniflask/oauth2/request.py
guniflask/oauth2/request_factory.py
guniflask/oauth2/token.py
guniflask-0.7.2.dist-info/LICENSE
guniflask-0.7.2.dist-info/METADATA
guniflask-0.7.2.dist-info/WHEEL
guniflask-0.7.2.dist-info/top_level.txt
guniflask-0.7.2.dist-info/RECORD
