Metadata-Version: 2.1
Name: guniflask
Version: 0.7.2
Summary: Better coding experience for Flask
Home-page: https://github.com/jadbin/guniflask
Author: jadbin
Author-email: jadbin.com@hotmail.com
License: MIT
Platform: UNKNOWN
Classifier: License :: OSI Approved :: MIT License
Classifier: Intended Audience :: Developers
Classifier: Programming Language :: Python
Classifier: Programming Language :: Python :: 3
Classifier: Programming Language :: Python :: 3.6
Classifier: Topic :: Software Development :: Libraries :: Python Modules
Requires-Python: >=3.6
Requires-Dist: Flask (>=1.1.1)
Requires-Dist: SQLAlchemy (>=1.3.13)
Requires-Dist: Flask-Cors (>=3.0.8)
Requires-Dist: PyJWT (>=1.7.1)
Requires-Dist: APScheduler (>=3.6.3)
Requires-Dist: requests (>=2.23.0)
